[
    {
        "package": "Cơ Bản",
        "price": "30.000",
        "desc": "Luyện đá, buff, relogin, speed..."
    },
    {
        "package": "Auto - nvhn",
        "price": "30.000",
        "desc": "Làm nvhn, tà thú, vượt ải"
    },
    {
        "package": "Auto Thí Luyện",
        "price": "50.000",
        "desc": "Auto thí luyện 4x → 6x → 12x"
    },
    {
        "package": "Up Làng Cổ",
        "price": "200.000",
        "desc": "Goback theo vị trí hoặc ATL (kèm cơ bản + lọc rác)"
    },
    {
        "package": "Goback hầm",
        "price": "70.000",
        "desc": "Up hầm: Goback hầm (trừ hầm 4 mới, hầm 3 không đánh vị trí)"
    },
    {
        "package": "Né PK",
        "price": "70.000",
        "desc": "Né PK – cứu sát theo HP, né bất kỳ ai"
    },
    {
        "package": "Né Tinh Anh - Thủ Lĩnh",
        "price": "150000",
        "desc": "Né toàn bộ TA - TL trong map"
    },
    {
        "package": "Lọc Đồ",
        "price": "50.000",
        "desc": "Lọc trang bị, trang sức, tbt, đá 4321..."
    },
    {
        "package": "Auto Chat",
        "price": "30.000",
        "desc": "AutoChat: Spam chậm thôi nha"
    },
    {
        "package": "Up Nhẫn Giả",
        "price": "100.000",
        "desc": "Auto farm tà thú, có chuyển map 24/24"
    }
